README.md
setup.py
pyx/__app__.py
pyx/__init__.py
pyx/app.py
pyx/main.py
pyx/pyx_parser.py
pyx/apps/app_fastapi.py
pyx/apps/app_flask.py
pyx/tags/__init__.py
pyx/tags/all.py
pyx/tags/default.py
pyx/tags/script.py
pyx/tags/select.py
pyx/tags/style.py
pyx/tags/tabs.py
pyx/utils/JSON.py
pyx/utils/__init__.py
pyx/utils/app.py
pyx/utils/children.py
pyx/utils/core.py
pyx/utils/dom.py
pyx/utils/id.py
pyx/utils/rand.py
pyx/utils/state.py
pyx_framework.egg-info/PKG-INFO
pyx_framework.egg-info/SOURCES.txt
pyx_framework.egg-info/dependency_links.txt
pyx_framework.egg-info/top_level.txt