Metadata-Version: 2.1
Name: pyx-framework
Version: 0.2.0
Summary: PYX - python-based realtime frontend framework
Home-page: https://github.com/kor0p/PYX#PYX
Author: kor0p
Author-email: 3.kor0p@gmail.com
License: GPLv3
Platform: UNKNOWN
Requires-Python: >=3.8
